{"totalSize": 2, "done": true, "records": [{"attributes": {"type": "Warriors__c", "url": "/services/data/v52.0/sobjects/Warriors__c/a035g000001X47MAAS"}, "LastModifiedById": "0055g00000BP3AQAA1", "CreatedById": "0055g00000BP3AQAA1", "OwnerId": "0055g00000BP3AQAA1", "Name": "Nam Dao Vip Pro 2", "Email__c": "nhd36@drexel.edu 2"}, {"attributes": {"type": "Warriors__c", "url": "/services/data/v52.0/sobjects/Warriors__c/a035g000001X47HAAS"}, "LastModifiedById": "0055g00000BP3AQAA1", "CreatedById": "0055g00000BP3AQAA1", "OwnerId": "0055g00000BP3AQAA1", "Name": "Nam Dao Vip Pro 2", "Email__c": "nhd36@drexel.edu 2"}]}